pocsuite3/__init__.py
pocsuite3/cli.py
pocsuite3/console.py
pocsuite3/api/__init__.py
pocsuite3/data/password-top100.txt
pocsuite3/lib/__init__.py
pocsuite3/lib/controller/__init__.py
pocsuite3/lib/controller/controller.py
pocsuite3/lib/core/__init__.py
pocsuite3/lib/core/clear.py
pocsuite3/lib/core/common.py
pocsuite3/lib/core/convert.py
pocsuite3/lib/core/data.py
pocsuite3/lib/core/datatype.py
pocsuite3/lib/core/decorators.py
pocsuite3/lib/core/docker_env.py
pocsuite3/lib/core/enums.py
pocsuite3/lib/core/exception.py
pocsuite3/lib/core/interpreter.py
pocsuite3/lib/core/interpreter_option.py
pocsuite3/lib/core/log.py
pocsuite3/lib/core/option.py
pocsuite3/lib/core/optiondict.py
pocsuite3/lib/core/plugin.py
pocsuite3/lib/core/poc.py
pocsuite3/lib/core/readlineng.py
pocsuite3/lib/core/register.py
pocsuite3/lib/core/revision.py
pocsuite3/lib/core/settings.py
pocsuite3/lib/core/shell.py
pocsuite3/lib/core/statistics_comparison.py
pocsuite3/lib/core/template.py
pocsuite3/lib/core/threads.py
pocsuite3/lib/core/update.py
pocsuite3/lib/helper/__init__.py
pocsuite3/lib/helper/archieve/__init__.py
pocsuite3/lib/helper/archieve/jar.py
pocsuite3/lib/helper/archieve/memoryzip.py
pocsuite3/lib/helper/archieve/war.py
pocsuite3/lib/helper/archieve/zip.py
pocsuite3/lib/helper/java/__init__.py
pocsuite3/lib/helper/java/serialization.py
pocsuite3/lib/parse/__init__.py
pocsuite3/lib/parse/cmd.py
pocsuite3/lib/parse/configfile.py
pocsuite3/lib/parse/dockerfile.py
pocsuite3/lib/parse/rules.py
pocsuite3/lib/parse/url.py
pocsuite3/lib/request/__init__.py
pocsuite3/lib/request/patch/__init__.py
pocsuite3/lib/request/patch/add_httpraw.py
pocsuite3/lib/request/patch/hook_request.py
pocsuite3/lib/request/patch/hook_request_redirect.py
pocsuite3/lib/request/patch/hook_urllib3_parse_url.py
pocsuite3/lib/request/patch/remove_ssl_verify.py
pocsuite3/lib/request/patch/remove_warnings.py
pocsuite3/lib/request/patch/session_reuse.py
pocsuite3/lib/request/patch/unquote_request_uri.py
pocsuite3-2.1.0.dist-info/COPYING
pocsuite3-2.1.0.dist-info/METADATA
pocsuite3-2.1.0.dist-info/WHEEL
pocsuite3-2.1.0.dist-info/entry_points.txt
pocsuite3-2.1.0.dist-info/top_level.txt
pocsuite3-2.1.0.dist-info/RECORD
