Metadata-Version: 2.2
Name: pocsuite3
Version: 2.1.0
Summary: Open-sourced remote vulnerability testing framework.
Home-page: https://pocsuite.org
Author: Knownsec 404 Team
Author-email: 404-team@knownsec.com
Maintainer: Knownsec 404 Team
License: GPLv2
Keywords: PoC,Exp,Pocsuite
Platform: any
Requires-Python: >=3.8
License-File: COPYING
Requires-Dist: requests>=2.22.0
Requires-Dist: requests-toolbelt
Requires-Dist: PySocks
Requires-Dist: urllib3
Requires-Dist: chardet
Requires-Dist: termcolor
Requires-Dist: colorama
Requires-Dist: prettytable
Requires-Dist: colorlog
Requires-Dist: scapy
Requires-Dist: Faker
Requires-Dist: pycryptodomex
Requires-Dist: dacite
Requires-Dist: PyYAML
Requires-Dist: lxml
Requires-Dist: docker
Requires-Dist: packaging
Provides-Extra: complete
Requires-Dist: pyOpenSSL; extra == "complete"
Requires-Dist: jq; extra == "complete"
Requires-Dist: mmh3; extra == "complete"
Dynamic: author
Dynamic: author-email
Dynamic: description
Dynamic: home-page
Dynamic: keywords
Dynamic: license
Dynamic: maintainer
Dynamic: platform
Dynamic: provides-extra
Dynamic: requires-dist
Dynamic: requires-python
Dynamic: summary
